{"output":{"type":"stdout"},"languages":{"java":{"taskClass":"AExpression","mainClass":"Main"}},"memoryLimit":256,"group":"Codeforces - Codeforces Round 274 (Div. 2)","batch":{"id":"c8b289a9-940d-4ae8-af28-9fb792df2202","size":1},"testType":"single","url":"https://codeforces.com/problemset/problem/479/A","interactive":false,"tests":[{"output":"9\n","status":"AC","stdout":"9\n","stderr":"","time_taken":0.029,"input":"1\n2\n3\n"},{"output":"60\n","status":"AC","stdout":"60\n","stderr":"","time_taken":0.029,"input":"2\n10\n3\n"}],"name":"A. Expression","timeLimit":1000,"input":{"type":"stdin"}}