{"group":"Codeforces - Codeforces Round 756 (Div. 3)","url":"https://codeforces.com/problemset/problem/1611/B","testType":"single","languages":{"java":{"taskClass":"BTeamCompositionProgrammersAndMathematicians","mainClass":"Main"}},"interactive":false,"input":{"type":"stdin"},"output":{"type":"stdout"},"tests":[{"input":"6\n5 5\n10 1\n2 3\n0 0\n17 2\n1000000000 1000000000\n","output":"2\n1\n1\n0\n2\n500000000\n","stdout":"2\n1\n1\n0\n2\n500000000\n","stderr":"","status":"AC","time_taken":0.034}],"name":"B. Team Composition: Programmers and Mathematicians","memoryLimit":256,"timeLimit":1000,"batch":{"id":"9d918076-fa36-4426-9fd0-8d8fdece9c7f","size":1}}