{"name":"C. Limited Repainting","memoryLimit":512,"group":"Codeforces - Educational Codeforces Round 175 (Rated for Div. 2)","languages":{"java":{"mainClass":"Main","taskClass":"CLimitedRepainting"}},"url":"https://codeforces.com/contest/2070/problem/C","output":{"type":"stdout"},"tests":[{"output":"3\n3\n0\n4\n0\n","stdout":"10\n10\n10\n7\n6\n","stderr":"","time_taken":0.029,"input":"5\n4 1\nBRBR\n9 3 5 4\n4 1\nBRBR\n9 5 3 4\n4 2\nBRBR\n9 3 5 4\n10 2\nBRBRBBRRBR\n5 1 2 4 5 3 6 1 5 4\n5 5\nRRRRR\n5 3 1 2 4\n","status":"WA"}],"interactive":false,"batch":{"size":1,"id":"8739fb6b-074a-4105-aea4-d599e6df93f7"},"testType":"single","input":{"type":"stdin"},"timeLimit":2000}