{"testType":"single","tests":[{"input":"5 7\n1 2 3\n1 3 1\n1 4 5\n2 3 2\n2 5 3\n3 4 2\n4 5 4\n","time_taken":0.009000000000000001,"stdout":"9\n8\n11\n8\n8\n8\n9\n","stderr":"","output":"9\n8\n11\n8\n8\n8\n9\n","status":"AC"}],"languages":{"java":{"taskClass":"EMinimumSpanningTreeForEachEdge","mainClass":"Main"}},"name":"E. Minimum spanning tree for each edge","input":{"type":"stdin"},"interactive":false,"group":"Codeforces - Educational Codeforces Round 3","batch":{"id":"8b94bf75-7bd7-4762-be4b-4e8ca308f2db","size":1},"url":"https://codeforces.com/problemset/problem/609/E","timeLimit":2000,"output":{"type":"stdout"},"memoryLimit":256}