{"group":"Codeforces - Educational Codeforces Round 29","timeLimit":2000,"name":"E. Turn Off The TV","testType":"single","languages":{"java":{"taskClass":"ETurnOffTheTV","mainClass":"Main"}},"batch":{"size":1,"id":"5c10561f-08e7-4b26-9473-2b313264c15d"},"tests":[{"stderr":"","status":"WA","selected":true,"input":"3\n1 3\n4 6\n1 7\n","output":"1\n","time_taken":0.048,"stdout":"2\n"},{"stderr":"","status":"AC","selected":true,"input":"2\n0 10\n0 10\n","output":"1\n","time_taken":0.038,"stdout":"1\n"},{"stderr":"","status":"AC","selected":true,"input":"3\n1 2\n3 4\n6 8\n","output":"-1\n","time_taken":0.043,"stdout":"-1\n"},{"stderr":"","status":"AC","selected":true,"input":"3\n1 2\n2 3\n3 4\n","output":"2\n","time_taken":0.045,"stdout":"2\n"}],"input":{"type":"stdin"},"interactive":false,"output":{"type":"stdout"},"url":"https://codeforces.com/contest/863/problem/E","memoryLimit":256}